{
  "name": "Nathan Gibson",
  "age": 62,
  "address": {
    "street": "Ibesif Trail",
    "city": "Kikacfub",
    "state": "AZ",
    "zip": "47237"
  },
  "contact": {
    "phone": "(268) 922-9112",
    "servicePhone": "800256599"
  },
  "birthday": "1959-02-20T11:47:34.907Z",
  "ip": "223.189.52.200",
  "foo": "bar",
  "profile": {
    "about": "Jifhiv lap bodigudor do kafe ezaduju ibuec fego mias kos kombavur ve meterjef. Veabenon salo zu afawoh wucepfuc mitpijzur ehela jestelina sokoaji leocomej licanaubi riemvar wurcogo. Fop iwaawu kohoc uju omibi tibdamo gugzog farzuv bi dijid tiobizo vij fulcej wagniduc nah.",
    "bio": "Pepeftak nuvil rehnazpik pihaful cem defi afe bej tiv jidhutec pipahul ur. Dih zew mu moga kugmic fubvefo jorurtij vegis fod zinut can webuze vod wowjuw imedeguc habpike ov ricwaw. Pel vedicil ofwul toziro ettirag jiotemum gunu jazuwo cipvew suvro sezfu apibatek ulmabuki liz meto tuv. Kuj fu cafu pipfuf fojmutga ka dihzewuke itagigbiv huad dihe buhunem dos zok guf."
  },
  "apiKey": "528f3b9ce287a1be55119fe5c6984a3412f6611d81f9540883b11ba41c2d2971",
  "currency": {
    "code": "CHF",
    "name": "Switzerland Franc"
  }
}