{
  "name": "Aiden Torres",
  "age": 45,
  "address": {
    "street": "Roma Place",
    "city": "Nuhinogu",
    "state": "CA",
    "zip": "43829"
  },
  "contact": {
    "phone": "(489) 637-1677",
    "servicePhone": "800942732"
  },
  "birthday": "1964-01-07T15:18:55.209Z",
  "ip": "152.254.20.41",
  "foo": "bar",
  "profile": {
    "about": "Ecko ip ba lefokhaz fo tospewam vod ragsam on esejuimi fed ga gon bo uhbavcic wejvi ju levo. Miwlumba re tohru cutwasbu uk hipge fuvvez legahwi navtakva fu oke irmag sapizdej wof caj mur. Pethan bumaz omovu havkodum ozmu barpi zud uc feage won nokuhale ami soecmo ko kuz ku reguwej diwmu. Faceuti vaznibeb wuhe afoca to nulkolno eglip ri atozabo hebfo nujbi nuvodnaj vucijbo dortap jeceun di indiltut finep. Boljafo nur uki luzsi fabfi ka cuj foz owuboopo porda huv luw vaz vugupacu dolpuuba rokup.",
    "bio": "Tapava mugogeje kacikzoh nehif otgokupa tuka onauni zitoh sec zolege ijepzaf iwazotec ge hewsiw funal. Riiv sihijug lu sewcul mopeb pu finoveun zashupita zufenu awu mig virir jik amoboifu loodaugo fijo redmup ku. Keztada pilnog dikjuvenu paglaag asinanfak ifiloje dobor ef velbop aviedad wuzo aboolu li ruhkeddud sehgestuz zavzador juduk. Sazoctac meitapi ub bec fedinu ponpasela tiemopan gar av geemego ced ja ejugomta. Ofgiz tespora uwirfir eg umid mucebtat tivli jusokzim seh uh lotef pudze catsa cajziok huka orodualu moh batej. Upahu jan iwevaw fijim wi mezudsej vo zoodu hocol hucgi ho zuk ho eca tohlire ogaitsu."
  },
  "apiKey": "e910b2670c959b55766e904c96a234e1a76ec41f2dc303d14298df8fd6cc41a4",
  "currency": {
    "code": "VUV",
    "name": "Vanuatu Vatu"
  }
}