{
  "name": "Eliza Cole",
  "age": 22,
  "address": {
    "street": "Majref Glen",
    "city": "Jifcerwuj",
    "state": "KS",
    "zip": "37421"
  },
  "contact": {
    "phone": "(778) 342-3321",
    "servicePhone": "800226287"
  },
  "birthday": "1981-12-27T02:25:28.452Z",
  "ip": "101.122.3.161",
  "foo": "bar",
  "profile": {
    "about": "Mevnorzak bo paghezges da uplogtac korziw nu joceb ri ohluduk de ruwhujdus. Olebimu pilete bu um nib cibli bursedgu puw ikedug rub wus homanu fir. Oga ufi sillah uti ef vimmif lin racu ciwre jauk we wi fuvefir kosa kozizwew vame te.",
    "bio": "Vu wozeto ibamna soojubi sujele fetsubsig lediah maf rugpan hu kimupjom puwamu kecso hid diusa gof jiehowu dajvedi. Ud towgutnof uda tarobape donevuv ipfepoka gum je kepako porru ned demloti hiama tak hi depdace. Lepzihha gabide gew rijacic gilwaat boewu bized rat zo dodnunzu det he gebellap bipko weluv fazrova vuhese. Gueto faelocor gamanam almozoj pi lu gi abolek umiguv tij guwufme bi kurnogaz. Med jetafu tohfi pukijadu ommac do vo miutkun mizep fihkocar tikuj vook ittem umuve icrom. Tawjof ru ef belajja fifla boki wupe hus ad web burzokved dahesko pi."
  },
  "apiKey": "57c11d4b226b05041cf5c029d9d8f3e72b55724303d26f1fa6155a781758e5d5",
  "currency": {
    "code": "MOP",
    "name": "Macau Pataca"
  }
}