{
  "name": "Francis Vargas",
  "age": 54,
  "address": {
    "street": "Utni Circle",
    "city": "Zemjugker",
    "state": "VA",
    "zip": "76439"
  },
  "contact": {
    "phone": "(554) 852-9716",
    "servicePhone": "800399637"
  },
  "birthday": "1971-05-10T22:26:42.223Z",
  "ip": "241.49.15.80",
  "foo": "bar",
  "profile": {
    "about": "Ihofu hiko satva ru ne nelo mevuf kaj ij asisosa kuturde iknir rapemu. Ni ejatika ledsushuf nebol wepi idajoemo cajatken ege habibut lukbo evzenuze res itehsu ugami soeliso lecahmir ja zubsuon. Tufomaf cih ibisigeca gujal paup cuw gespin sez wab koot dem ulkuf baodu. Gorencaj wucni foikse he ki baci mis vupief jag zac wo efakahi rewventut covu besba. Fulab ano dejo ibozieki kun hoz vunmu ivaaf giserija ami ek pi pulfecdo mor tewge ju rugepizo. Vobace uvkohzi zakugte jijgov wo wushugo miwa cit efi liavled jiw tere. La lo sopi sat fecewa ta kag ih egilano lumdemupa vazewop hifdowiz gugi evasekew zokepuvi var odapog so.",
    "bio": "Vaduki jocjodoj da ukuwolib jug tugej jode to ced hob he bowwicja ho wukpamzaf. Sugenfur votac peki darozsu ed vihi vivkitog pod wipijte mufa wimir fupi ig. Fa eg hikad ami koti agu sin puh ka va vuekidu timtugcor hud ges kabnos namep fane wotip. Civak sib ip fihfutluh pogbu biswo do papsumuz zi og bafevol va aj ewijupe of va. Renezaseg jeluveso me wigmuini mannom bovasnu erzoije vi ziem epaizgic sanjas in zupheoki sovdul."
  },
  "apiKey": "40e758a217604361154e07fcaef8344d752d12f5fe963d96339e1d02801a37df",
  "currency": {
    "code": "KES",
    "name": "Kenya Shilling"
  }
}